final_package_203/__init__.py
final_package_203/backtest.py
final_package_203/class_basket.py
final_package_203/final_package_203.py
final_package_203/opti_basket.ipynb
final_package_203/performance_comparator.ipynb
final_package_203/stats.py
final_package_203-0.4.0.dist-info/LICENSE
final_package_203-0.4.0.dist-info/METADATA
final_package_203-0.4.0.dist-info/WHEEL
final_package_203-0.4.0.dist-info/RECORD
