Metadata-Version: 2.3
Name: final_package_203
Version: 0.4.0
Summary: A package for backtesting optimized basket.
License: MIT
Author: Caroline
Requires-Python: >=3.11,<4.0
Classifier: License :: OSI Approved :: MIT License
Classifier: Programming Language :: Python :: 3
Classifier: Programming Language :: Python :: 3.11
Classifier: Programming Language :: Python :: 3.12
Classifier: Programming Language :: Python :: 3.13
Requires-Dist: jupyter (>=1.1.1,<2.0.0)
Requires-Dist: pybacktestchain (>=0.2.1,<0.3.0)
